bench_utils/__init__.py
bench_utils/profileit.py
bench_utils/timeit.py
bench_utils-1.0.3.dist-info/LICENSE
bench_utils-1.0.3.dist-info/METADATA
bench_utils-1.0.3.dist-info/WHEEL
bench_utils-1.0.3.dist-info/entry_points.txt
bench_utils-1.0.3.dist-info/top_level.txt
bench_utils-1.0.3.dist-info/RECORD
