Metadata-Version: 2.1
Name: bench-utils
Version: 1.0.3
Summary: A collection of benchmarking tools.
Home-page: https://github.com/drkostas/bench-utils/tree/master/
Author: Kostas Georgiou
Author-email: georgiou.kostas94@gmail.com
License: Apache Software License 2.0
Keywords: benchmark,bench,profiling,timing,tools,utils
Platform: UNKNOWN
Classifier: Development Status :: 5 - Production/Stable
Classifier: Intended Audience :: Developers
Classifier: License :: OSI Approved :: Apache Software License
Classifier: Natural Language :: English
Classifier: Programming Language :: Python :: 3.6
Classifier: Programming Language :: Python :: 3.7
Classifier: Programming Language :: Python :: 3.8
Requires-Python: >=3.6
License-File: LICENSE
Requires-Dist: termcolor-logger (>=1.0.2)
